invenio_moodle/__init__.py
invenio_moodle/cli.py
invenio_moodle/config.py
invenio_moodle/ext.py
invenio_moodle/jobs.py
invenio_moodle/proxies.py
invenio_moodle/records.py
invenio_moodle/schemas.py
invenio_moodle/services.py
invenio_moodle/tasks.py
invenio_moodle/types.py
invenio_moodle/utils.py
invenio_moodle-1.1.3.dist-info/licenses/AUTHORS.rst
invenio_moodle-1.1.3.dist-info/licenses/LICENSE
invenio_moodle-1.1.3.dist-info/METADATA
invenio_moodle-1.1.3.dist-info/WHEEL
invenio_moodle-1.1.3.dist-info/entry_points.txt
invenio_moodle-1.1.3.dist-info/top_level.txt
invenio_moodle-1.1.3.dist-info/RECORD
