Metadata-Version: 2.4
Name: invenio-moodle
Version: 1.1.3
Summary: "Provides API for Moodle."
Home-page: https://github.com/tu-graz-library/invenio-moodle
Author: "Graz University of Technology"
Author-email: info@tugraz.at
License: MIT
Keywords: invenio_moodle invenio moodle teachcenter
Platform: any
Classifier: Programming Language :: Python :: 3.12
Classifier: Programming Language :: Python :: 3.13
Requires-Python: >=3.12
License-File: LICENSE
License-File: AUTHORS.rst
Requires-Dist: click>=8.0.0
Requires-Dist: click-params>=0.4.0
Requires-Dist: invenio-celery>=1.2.5
Requires-Dist: invenio-jobs>=3.0.0
Requires-Dist: requests>=2.0.0
Provides-Extra: tests
Requires-Dist: flask-principal>=0.4.0; extra == "tests"
Requires-Dist: invenio-app>=2.0.0; extra == "tests"
Requires-Dist: invenio-access>=2.0.0; extra == "tests"
Requires-Dist: invenio-i18n>=2.1.0; extra == "tests"
Requires-Dist: invenio-records-resources>=5.0.0; extra == "tests"
Requires-Dist: invenio-search[opensearch2]>=2.3.0; extra == "tests"
Requires-Dist: marshmallow>=3.0.0; extra == "tests"
Requires-Dist: pytest-black-ng>=0.4.0; extra == "tests"
Requires-Dist: pytest-invenio>=1.4.3; extra == "tests"
Requires-Dist: ruff>=0.4.10; extra == "tests"
Requires-Dist: Sphinx>=4.4.0; extra == "tests"
Requires-Dist: sphinx-autodoc-typehints>=1.10.3; extra == "tests"
Dynamic: license-file
